[{"_id":"615351b203385c0016b88437","dateRange":{"_id":"615351b203385c0016b88438","startDate":640,"endDate":703},"note":null,"allyEntries":[{"_id":"615351b203385c0016b88439","name":"Nepalese ally","allyArmyList":{"_id":"6153519a03385c0016b84892","name":"Nepalese ally","listId":296,"sublistId":"z","dateRange":null,"troopOptions":[{"_id":"6153519a03385c0016b84893","min":2,"max":6,"dateRanges":[],"troopEntries":[{"_id":"6153519a03385c0016b84894","troopTypeCode":"HBW","dismountTypeCode":null,"note":null}],"description":"Nepalese horse archers","note":"","core":"","battleCardEntries":[]},{"_id":"6153519a03385c0016b84895","min":0,"max":1,"dateRanges":[],"troopEntries":[{"_id":"6153519a03385c0016b84896","troopTypeCode":"RDR","dismountTypeCode":null,"note":null}],"description":"Nepalese swordsmen","note":"","core":"","battleCardEntries":[]},{"_id":"6153519a03385c0016b84897","min":0,"max":2,"dateRanges":[],"troopEntries":[{"_id":"6153519a03385c0016b84898","troopTypeCode":"SKM","dismountTypeCode":null,"note":null}],"description":"Nepalese skirmishing bowmen","note":"","core":"","battleCardEntries":[]}],"internalContingent":false,"__v":0}}]},{"_id":"615351b203385c0016b8843a","dateRange":{"_id":"615351b203385c0016b8843b","startDate":660,"endDate":848},"note":null,"allyEntries":[{"_id":"615351b203385c0016b8843c","name":"Türgesh, Qarluq, Ferghanan or other Turkic allies","allyArmyList":{"_id":"6153519a03385c0016b847dd","name":"Central Asian Turkish","listId":287,"sublistId":"b","dateRange":{"_id":"6153508803385c0016b82301","startDate":550,"endDate":1330},"troopOptions":[{"_id":"6153519a03385c0016b847df","min":0,"max":1,"dateRanges":[],"troopEntries":[{"_id":"6153519a03385c0016b847e0","troopTypeCode":"HBW","dismountTypeCode":null,"note":null}],"description":"Noble horse archers","note":"","core":"","battleCardEntries":[]},{"_id":"6153519a03385c0016b847e1","min":1,"max":2,"dateRanges":[],"troopEntries":[{"_id":"6153519a03385c0016b847e2","troopTypeCode":"HBW","dismountTypeCode":null,"note":null}],"description":"Horse archers","note":"","core":"","battleCardEntries":[]}],"internalContingent":false,"armyListId":"5fb1b9efe1af06001770a068","__v":0}}]},{"_id":"615351b203385c0016b8843d","dateRange":{"_id":"615351b203385c0016b8843e","startDate":670,"endDate":692},"note":null,"allyEntries":[{"_id":"615351b203385c0016b8843f","name":"Khotanese ally","allyArmyList":{"_id":"6153519a03385c0016b847ef","name":"Tarim Basin Citystates","listId":288,"sublistId":"b","dateRange":{"_id":"6153508803385c0016b8230d","startDate":500,"endDate":1000},"troopOptions":[{"_id":"6153519a03385c0016b847f1","min":1,"max":2,"dateRanges":[],"troopEntries":[{"_id":"6153519a03385c0016b847f2","troopTypeCode":"ECV","dismountTypeCode":null,"note":null}],"description":"Dihqan armored horsemen","note":"","core":"","battleCardEntries":[]},{"_id":"6153519a03385c0016b847f3","min":0,"max":2,"dateRanges":[],"troopEntries":[{"_id":"6153519a03385c0016b847f4","troopTypeCode":"HBW","dismountTypeCode":null,"note":null}],"description":"Dihqan horsemen with lesser armor, or scout or local nomad horse archers","note":"","core":"","battleCardEntries":[]},{"_id":"6153519a03385c0016b847f5","min":1,"max":1,"dateRanges":[],"troopEntries":[{"_id":"6153519a03385c0016b847f6","troopTypeCode":"BLV","dismountTypeCode":null,"note":null}],"description":"Bowmen","note":"","core":"all","battleCardEntries":[]}],"internalContingent":false,"armyListId":"5fb1b9efe1af06001770a074","__v":0}}]},{"_id":"615351b203385c0016b88440","dateRange":{"_id":"615351b203385c0016b88441","startDate":707,"endDate":707},"note":null,"allyEntries":[{"_id":"615351b203385c0016b88442","name":"Sogdian ally","allyArmyList":{"_id":"6153519a03385c0016b847e3","name":"Sogdians","listId":288,"sublistId":"a","dateRange":{"_id":"6153508803385c0016b82307","startDate":500,"endDate":730},"troopOptions":[{"_id":"6153519a03385c0016b847e5","min":1,"max":2,"dateRanges":[],"troopEntries":[{"_id":"6153519a03385c0016b847e6","troopTypeCode":"KNT","dismountTypeCode":null,"note":null}],"description":"Chakar","note":"","core":"","battleCardEntries":[]},{"_id":"6153519a03385c0016b847e7","min":0,"max":1,"dateRanges":[],"troopEntries":[{"_id":"6153519a03385c0016b847e8","troopTypeCode":"ECV","dismountTypeCode":null,"note":null},{"_id":"6153519a03385c0016b847e9","troopTypeCode":"HBW","dismountTypeCode":null,"note":null}],"description":"Dihqan armored horsemen","note":"","core":"","battleCardEntries":[]},{"_id":"6153519a03385c0016b847ea","min":0,"max":1,"dateRanges":[],"troopEntries":[{"_id":"6153519a03385c0016b847eb","troopTypeCode":"HBW","dismountTypeCode":null,"note":null}],"description":"Scout or local nomad horse archers","note":"","core":"","battleCardEntries":[]},{"_id":"6153519a03385c0016b847ec","min":1,"max":1,"dateRanges":[],"troopEntries":[{"_id":"6153519a03385c0016b847ed","troopTypeCode":"ARC","dismountTypeCode":null,"note":null},{"_id":"6153519a03385c0016b847ee","troopTypeCode":"BLV","dismountTypeCode":null,"note":null}],"description":"Bowmen","note":"","core":"all","battleCardEntries":[]}],"internalContingent":false,"armyListId":"5fb1b9efe1af06001770a06e","__v":0}}]},{"_id":"615351b203385c0016b88443","dateRange":{"_id":"615351b203385c0016b88444","startDate":754,"endDate":793},"note":null,"allyEntries":[{"_id":"615351b203385c0016b88445","name":"Nanzhao ally","allyArmyList":{"_id":"6153519a03385c0016b848b1","name":"Nanzhao and Dali","listId":298,"sublistId":"a","dateRange":{"_id":"6153508903385c0016b82391","startDate":728,"endDate":1382},"troopOptions":[{"_id":"6153519a03385c0016b848b3","min":0,"max":1,"dateRanges":[],"troopEntries":[{"_id":"6153519a03385c0016b848b4","troopTypeCode":"ECV","dismountTypeCode":null,"note":null},{"_id":"6153519a03385c0016b848b5","troopTypeCode":"HBW","dismountTypeCode":null,"note":null}],"description":"Horse archers with hide armor armed with bow or crossbow, plus spear","note":"","core":"","battleCardEntries":[]},{"_id":"6153519a03385c0016b848b6","min":0,"max":1,"dateRanges":[],"troopEntries":[{"_id":"6153519a03385c0016b848b7","troopTypeCode":"PIK","dismountTypeCode":null,"note":null}],"description":"Fupai guards in hide armor armed with very long spears","note":"","core":"all","battleCardEntries":[]},{"_id":"6153519a03385c0016b848b8","min":1,"max":2,"dateRanges":[],"troopEntries":[{"_id":"6153519a03385c0016b848b9","troopTypeCode":"LSP","dismountTypeCode":null,"note":null}],"description":"Unarmored spearmen","note":"","core":"all","battleCardEntries":[]},{"_id":"6153519a03385c0016b848ba","min":0,"max":1,"dateRanges":[],"troopEntries":[{"_id":"6153519a03385c0016b848bb","troopTypeCode":"BLV","dismountTypeCode":null,"note":null},{"_id":"6153519a03385c0016b848bc","troopTypeCode":"ARC","dismountTypeCode":null,"note":null}],"description":"Bowmen, unarmored or with hide armor or shield","note":"","core":"all","battleCardEntries":[]},{"_id":"6153519a03385c0016b848bd","min":0,"max":1,"dateRanges":[{"_id":"6153519a03385c0016b848be","startDate":794,"endDate":1382}],"troopEntries":[{"_id":"6153519a03385c0016b848bf","troopTypeCode":"ARC","dismountTypeCode":null,"note":null}],"description":"Crossbowmen","note":"","core":"all","battleCardEntries":[]},{"_id":"6153519a03385c0016b848c0","min":0,"max":1,"dateRanges":[],"troopEntries":[{"_id":"6153519a03385c0016b848c1","troopTypeCode":"WBD","dismountTypeCode":null,"note":null}],"description":"Tribal fighters","note":"","core":"","battleCardEntries":[]}],"internalContingent":false,"armyListId":"5fb1b9f0e1af06001770a0f7","__v":0}}]},{"_id":"615351b203385c0016b88446","dateRange":{"_id":"615351b203385c0016b88447","startDate":795,"endDate":801},"note":null,"allyEntries":[{"_id":"615351b203385c0016b88448","name":"Abbasid contingent","allyArmyList":{"_id":"6153519a03385c0016b8488c","name":"Abbasid Contingent","listId":296,"sublistId":"x","dateRange":null,"troopOptions":[{"_id":"6153519a03385c0016b8488d","min":1,"max":1,"dateRanges":[],"troopEntries":[{"_id":"6153519a03385c0016b8488e","troopTypeCode":"JCV","dismountTypeCode":null,"note":null},{"_id":"6153519a03385c0016b8488f","troopTypeCode":"ECV","dismountTypeCode":null,"note":null}],"description":"Abbasid heavy horsemen","note":"","core":"","battleCardEntries":[]},{"_id":"6153519a03385c0016b84890","min":0,"max":1,"dateRanges":[],"troopEntries":[{"_id":"6153519a03385c0016b84891","troopTypeCode":"HFT","dismountTypeCode":null,"note":null}],"description":"Abbasid infantry","note":"","core":"","battleCardEntries":[]}],"internalContingent":false,"__v":0}}]}]