[{"_id":"615351a003385c0016b852da","dateRange":null,"note":null,"allyEntries":[{"_id":"615351a003385c0016b852db","name":"Urartian allies","allyArmyList":{"_id":"6153518e03385c0016b83662","name":"Urartian","listId":34,"sublistId":"a","dateRange":{"_id":"6153507303385c0016b816b8","startDate":-880,"endDate":-585},"troopOptions":[{"_id":"6153518e03385c0016b83664","min":0,"max":1,"dateRanges":[{"_id":"6153518e03385c0016b83665","startDate":-880,"endDate":-765}],"troopEntries":[{"_id":"6153518e03385c0016b83666","troopTypeCode":"BAD","dismountTypeCode":null,"note":null}],"description":"Mounted fighters","note":"","core":"","battleCardEntries":[]},{"_id":"6153518e03385c0016b83667","min":0,"max":1,"dateRanges":[{"_id":"6153518e03385c0016b83668","startDate":-764,"endDate":-585}],"troopEntries":[{"_id":"6153518e03385c0016b83669","troopTypeCode":"JCV","dismountTypeCode":null,"note":null}],"description":"Kallupu horsemen","note":"","core":"","battleCardEntries":[]},{"_id":"6153518e03385c0016b8366a","min":2,"max":4,"dateRanges":[],"troopEntries":[{"_id":"6153518e03385c0016b8366b","troopTypeCode":"LFT","dismountTypeCode":null,"note":null}],"description":"Close-combat infantry","note":"","core":"all","battleCardEntries":[]},{"_id":"6153518e03385c0016b8366c","min":0,"max":1,"dateRanges":[{"_id":"6153518e03385c0016b8366d","startDate":-764,"endDate":-585}],"troopEntries":[{"_id":"6153518e03385c0016b8366e","troopTypeCode":"RDR","dismountTypeCode":null,"note":null}],"description":"Royal army infantry","note":"","core":"all","battleCardEntries":[]},{"_id":"6153518e03385c0016b8366f","min":0,"max":2,"dateRanges":[],"troopEntries":[{"_id":"6153518e03385c0016b83670","troopTypeCode":"SKM","dismountTypeCode":null,"note":null}],"description":"Skirmishing bowmen and slingers","note":"","core":"","battleCardEntries":[]}],"internalContingent":false,"armyListId":"5fb1b9dae1af060017709412","__v":0}}]},{"_id":"615351a003385c0016b852dc","dateRange":null,"note":null,"allyEntries":[{"_id":"615351a003385c0016b852dd","name":"Kimmerian allies","allyArmyList":{"_id":"6153518e03385c0016b83696","name":"Kimmerian and Skythian","listId":38,"sublistId":"a","dateRange":{"_id":"6153507403385c0016b816d6","startDate":-722,"endDate":-300},"troopOptions":[{"_id":"6153518e03385c0016b83698","min":0,"max":1,"dateRanges":[{"_id":"6153518e03385c0016b83699","startDate":-500,"endDate":-300}],"troopEntries":[{"_id":"6153518e03385c0016b8369a","troopTypeCode":"ECV","dismountTypeCode":null,"note":null}],"description":"Noble armored horsemen","note":"","core":"all","battleCardEntries":[]},{"_id":"6153518e03385c0016b8369b","min":1,"max":4,"dateRanges":[],"troopEntries":[{"_id":"6153518e03385c0016b8369c","troopTypeCode":"HBW","dismountTypeCode":null,"note":null}],"description":"Horse archers","note":"","core":"","battleCardEntries":[]}],"internalContingent":false,"armyListId":"5fb1b9dae1af060017709430","__v":0}}]}]