[{"_id":"5fb1ba21e1af06001770c196","dateRange":null,"note":null,"allyEntries":[{"_id":"5fb1ba21e1af06001770c197","name":"Phoenician allies","allyArmyList":{"_id":"5fb1ba08e1af06001770a67f","name":"Early Cypriot and Phoenician","listId":32,"sublistId":"a","dateRange":{"_id":"5fb1b9dae1af0600177093f6","startDate":-1000,"endDate":-665},"troopOptions":[],"internalContingent":false,"armyListId":"5fb1b9dae1af0600177093f2","__v":0}}]},{"_id":"5fb1ba21e1af06001770c198","dateRange":null,"note":null,"allyEntries":[{"_id":"5fb1ba21e1af06001770c199","name":"Phoenician allies","allyArmyList":{"_id":"5fb1ba08e1af06001770a681","name":"Middle Cypriot and Phoenician","listId":32,"sublistId":"b","dateRange":{"_id":"5fb1b9dae1af0600177093fd","startDate":-664,"endDate":-351},"troopOptions":[{"_id":"5fb1ba08e1af06001770a683","min":0,"max":1,"dateRange":{"_id":"5fb1ba08e1af06001770a684","startDate":-664,"endDate":-490},"troopEntries":[{"_id":"5fb1ba08e1af06001770a685","troopTypeCode":"CHT","dismountTypeCode":null,"note":null}],"description":"4-horse chariots with three crewmen","note":"","core":"","battleCardEntries":[]},{"_id":"5fb1ba08e1af06001770a686","min":2,"max":5,"dateRange":null,"troopEntries":[{"_id":"5fb1ba08e1af06001770a687","troopTypeCode":"LFT","dismountTypeCode":null,"note":null},{"_id":"5fb1ba08e1af06001770a688","troopTypeCode":"HFT","dismountTypeCode":null,"note":null}],"description":"Spearmen or hoplites","note":"","core":"all","battleCardEntries":[]},{"_id":"5fb1ba08e1af06001770a689","min":0,"max":1,"dateRange":null,"troopEntries":[{"_id":"5fb1ba08e1af06001770a68a","troopTypeCode":"BLV","dismountTypeCode":null,"note":null}],"description":"Bowmen","note":"","core":"all","battleCardEntries":[]}],"internalContingent":false,"armyListId":"5fb1b9dae1af0600177093f9","__v":0}}]},{"_id":"5fb1ba21e1af06001770c19a","dateRange":null,"note":null,"allyEntries":[{"_id":"5fb1ba21e1af06001770c19b","name":"Aramaean allies","allyArmyList":{"_id":"5fb1ba08e1af06001770a65a","name":"Early Syro-Hittite","listId":30,"sublistId":"a","dateRange":{"_id":"5fb1b9dae1af0600177093e1","startDate":-1100,"endDate":-901},"troopOptions":[{"_id":"5fb1ba08e1af06001770a65c","min":0,"max":1,"dateRange":null,"troopEntries":[{"_id":"5fb1ba08e1af06001770a65d","troopTypeCode":"CHT","dismountTypeCode":null,"note":null}],"description":"2-horse chariots with two crewmen","note":"","core":"","battleCardEntries":[]},{"_id":"5fb1ba08e1af06001770a65e","min":2,"max":3,"dateRange":null,"troopEntries":[{"_id":"5fb1ba08e1af06001770a65f","troopTypeCode":"LFT","dismountTypeCode":null,"note":null}],"description":"Militia spearmen","note":"","core":"all","battleCardEntries":[]},{"_id":"5fb1ba08e1af06001770a660","min":0,"max":2,"dateRange":null,"troopEntries":[{"_id":"5fb1ba08e1af06001770a661","troopTypeCode":"BLV","dismountTypeCode":null,"note":null}],"description":"Militia bowmen","note":"","core":"all","battleCardEntries":[]},{"_id":"5fb1ba08e1af06001770a662","min":0,"max":2,"dateRange":null,"troopEntries":[{"_id":"5fb1ba08e1af06001770a663","troopTypeCode":"SKM","dismountTypeCode":null,"note":null}],"description":"Militia slingers","note":"","core":"","battleCardEntries":[]}],"internalContingent":false,"armyListId":"5fb1b9dae1af0600177093dd","__v":0}}]},{"_id":"5fb1ba21e1af06001770c19c","dateRange":null,"note":null,"allyEntries":[{"_id":"5fb1ba21e1af06001770c19d","name":"Aramaean allies","allyArmyList":{"_id":"5fb1ba08e1af06001770a664","name":"Later Syro-Hittite","listId":30,"sublistId":"b","dateRange":{"_id":"5fb1b9dae1af0600177093e8","startDate":-900,"endDate":-710},"troopOptions":[{"_id":"5fb1ba08e1af06001770a666","min":1,"max":2,"dateRange":null,"troopEntries":[{"_id":"5fb1ba08e1af06001770a667","troopTypeCode":"CHT","dismountTypeCode":null,"note":null}],"description":"2-horse chariots with two crewmen, or 3- or 4-horse chariots with three crewmen","note":"","core":"","battleCardEntries":[]},{"_id":"5fb1ba08e1af06001770a668","min":1,"max":2,"dateRange":null,"troopEntries":[{"_id":"5fb1ba08e1af06001770a669","troopTypeCode":"LFT","dismountTypeCode":null,"note":null}],"description":"Militia spearmen","note":"","core":"all","battleCardEntries":[]},{"_id":"5fb1ba08e1af06001770a66a","min":0,"max":1,"dateRange":null,"troopEntries":[{"_id":"5fb1ba08e1af06001770a66b","troopTypeCode":"BLV","dismountTypeCode":null,"note":null}],"description":"Militia bowmen","note":"","core":"all","battleCardEntries":[]},{"_id":"5fb1ba08e1af06001770a66c","min":0,"max":1,"dateRange":null,"troopEntries":[{"_id":"5fb1ba08e1af06001770a66d","troopTypeCode":"SKM","dismountTypeCode":null,"note":null}],"description":"Militia slingers","note":"","core":"","battleCardEntries":[]}],"internalContingent":false,"armyListId":"5fb1b9dae1af0600177093e4","__v":0}}]},{"_id":"5fb1ba21e1af06001770c19e","dateRange":{"_id":"5fb1ba21e1af06001770c19f","startDate":-743,"endDate":-720},"note":null,"allyEntries":[{"_id":"5fb1ba21e1af06001770c1a0","name":"Egyptian allies","allyArmyList":{"_id":"5fb1ba08e1af06001770a742","name":"Libyan Egyptian","listId":43,"sublistId":"a","dateRange":{"_id":"5fb1b9dbe1af06001770946e","startDate":-946,"endDate":-712},"troopOptions":[{"_id":"5fb1ba08e1af06001770a744","min":0,"max":1,"dateRange":null,"troopEntries":[{"_id":"5fb1ba08e1af06001770a745","troopTypeCode":"CHT","dismountTypeCode":null,"note":null}],"description":"2-horse chariots","note":"","core":"","battleCardEntries":[]},{"_id":"5fb1ba08e1af06001770a746","min":1,"max":2,"dateRange":null,"troopEntries":[{"_id":"5fb1ba08e1af06001770a747","troopTypeCode":"WRR","dismountTypeCode":null,"note":null}],"description":"Meshwesh","note":"","core":"all","battleCardEntries":[]},{"_id":"5fb1ba08e1af06001770a748","min":1,"max":2,"dateRange":null,"troopEntries":[{"_id":"5fb1ba08e1af06001770a749","troopTypeCode":"RBL","dismountTypeCode":null,"note":null}],"description":"Libu, Palestinian, or Arab javelinmen","note":"","core":"","battleCardEntries":[]},{"_id":"5fb1ba08e1af06001770a74a","min":0,"max":1,"dateRange":null,"troopEntries":[{"_id":"5fb1ba08e1af06001770a74b","troopTypeCode":"SKM","dismountTypeCode":null,"note":null}],"description":"Nubian or Libu skirmishing bowmen","note":"","core":"","battleCardEntries":[]},{"_id":"5fb1ba08e1af06001770a74c","min":0,"max":1,"dateRange":null,"troopEntries":[{"_id":"5fb1ba08e1af06001770a74d","troopTypeCode":"LFT","dismountTypeCode":null,"note":null}],"description":"Egyptian infantry","note":"","core":"all","battleCardEntries":[]},{"_id":"5fb1ba08e1af06001770a74e","min":0,"max":1,"dateRange":null,"troopEntries":[{"_id":"5fb1ba08e1af06001770a74f","troopTypeCode":"BLV","dismountTypeCode":null,"note":null}],"description":"Egyptian bowmen","note":"","core":"all","battleCardEntries":[]}],"internalContingent":false,"armyListId":"5fb1b9dbe1af06001770946a","__v":0}}]},{"_id":"5fb1ba21e1af06001770c1a1","dateRange":{"_id":"5fb1ba21e1af06001770c1a2","startDate":-701,"endDate":-701},"note":null,"allyEntries":[{"_id":"5fb1ba21e1af06001770c1a3","name":"Egyptian allies","allyArmyList":{"_id":"5fb1ba09e1af06001770a75e","name":"Kushite Egyptian","listId":44,"sublistId":"b","dateRange":{"_id":"5fb1b9dbe1af06001770947d","startDate":-745,"endDate":-593},"troopOptions":[{"_id":"5fb1ba09e1af06001770a760","min":0,"max":1,"dateRange":null,"troopEntries":[{"_id":"5fb1ba09e1af06001770a761","troopTypeCode":"CHT","dismountTypeCode":null,"note":null}],"description":"2-horse chariots (also possibly 4-horse chariots with three crewmen after 727 BC)","note":"","core":"","battleCardEntries":[]},{"_id":"5fb1ba09e1af06001770a762","min":0,"max":1,"dateRange":null,"troopEntries":[{"_id":"5fb1ba09e1af06001770a763","troopTypeCode":"JCV","dismountTypeCode":null,"note":null}],"description":"Kushite horsemen","note":"","core":"","battleCardEntries":[]},{"_id":"5fb1ba09e1af06001770a764","min":1,"max":3,"dateRange":null,"troopEntries":[{"_id":"5fb1ba09e1af06001770a765","troopTypeCode":"ARC","dismountTypeCode":null,"note":null},{"_id":"5fb1ba09e1af06001770a766","troopTypeCode":"SKM","dismountTypeCode":null,"note":null}],"description":"Kushite bowmen","note":"","core":"all","battleCardEntries":[]},{"_id":"5fb1ba09e1af06001770a767","min":0,"max":1,"dateRange":null,"troopEntries":[{"_id":"5fb1ba09e1af06001770a768","troopTypeCode":"LFT","dismountTypeCode":null,"note":null}],"description":"Kushite javelinmen","note":"","core":"","battleCardEntries":[]},{"_id":"5fb1ba09e1af06001770a769","min":0,"max":1,"dateRange":null,"troopEntries":[{"_id":"5fb1ba09e1af06001770a76a","troopTypeCode":"SKM","dismountTypeCode":null,"note":null}],"description":"Kushite skirmishing slingers","note":"","core":"","battleCardEntries":[]}],"internalContingent":false,"armyListId":"5fb1b9dbe1af060017709478","__v":0}}]}]