[{"_id":"5fb1ba28e1af06001770cc97","dateRange":{"_id":"5fb1ba28e1af06001770cc98","startDate":-207,"endDate":-207},"note":null,"allyEntries":[{"_id":"5fb1ba28e1af06001770cc99","name":"(Eleian) Roman allies","allyArmyList":{"_id":"5fb1ba0ae1af06001770a928","name":"Polybian Roman","listId":68,"sublistId":"a","dateRange":{"_id":"5fb1b9dde1af0600177095c4","startDate":-275,"endDate":-105},"troopOptions":[{"_id":"5fb1ba0ae1af06001770a92a","min":1,"max":3,"dateRange":null,"troopEntries":[{"_id":"5fb1ba0ae1af06001770a92b","troopTypeCode":"EFT","dismountTypeCode":null,"note":null}],"description":"Legionaries","note":"","core":"all","battleCardEntries":[]},{"_id":"5fb1ba0ae1af06001770a92c","min":0,"max":1,"dateRange":null,"troopEntries":[{"_id":"5fb1ba0ae1af06001770a92d","troopTypeCode":"HFT","dismountTypeCode":null,"note":null}],"description":"Raw, mutinous, or recently recruited legionaries","note":"","core":"all","battleCardEntries":[]},{"_id":"5fb1ba0ae1af06001770a92e","min":0,"max":3,"dateRange":{"_id":"5fb1ba0ae1af06001770a92f","startDate":-225,"endDate":-211},"troopEntries":[{"_id":"5fb1ba0ae1af06001770a930","troopTypeCode":"HFT","dismountTypeCode":null,"note":null}],"description":"Large numbers of recently recruited legionaries","note":"only in Italy","core":"all","battleCardEntries":[]},{"_id":"5fb1ba0ae1af06001770a931","min":0,"max":1,"dateRange":{"_id":"5fb1ba0ae1af06001770a932","startDate":-275,"endDate":-211},"troopEntries":[{"_id":"5fb1ba0ae1af06001770a933","troopTypeCode":"RBL","dismountTypeCode":null,"note":null}],"description":"Leves","note":"","core":"","battleCardEntries":[]},{"_id":"5fb1ba0ae1af06001770a934","min":0,"max":1,"dateRange":{"_id":"5fb1ba0ae1af06001770a935","startDate":-210,"endDate":-105},"troopEntries":[{"_id":"5fb1ba0ae1af06001770a936","troopTypeCode":"LFT","dismountTypeCode":null,"note":null}],"description":"Velites","note":"","core":"","battleCardEntries":[]},{"_id":"5fb1ba0ae1af06001770a937","min":0,"max":1,"dateRange":null,"troopEntries":[{"_id":"5fb1ba0ae1af06001770a938","troopTypeCode":"BAD","dismountTypeCode":null,"note":null}],"description":"Italian allied horsemen or hamippoi (light foot mixed with cavalry)","note":"","core":"","battleCardEntries":[]},{"_id":"5fb1ba0ae1af06001770a939","min":0,"max":1,"dateRange":null,"troopEntries":[{"_id":"5fb1ba0ae1af06001770a93a","troopTypeCode":"SKM","dismountTypeCode":null,"note":null}],"description":"Skirmishing bowmen and slingers","note":"","core":"","battleCardEntries":[]}],"internalContingent":false,"armyListId":"5fb1b9dde1af0600177095c0","__v":0}}]}]