[{"_id":"5fb1ba3de1af06001770f453","dateRange":{"_id":"5fb1ba3de1af06001770f454","startDate":1241,"endDate":1270},"note":null,"allyEntries":[{"_id":"5fb1ba3de1af06001770f455","name":"(Tambralinga Malays) Sinhalese allies","allyArmyList":{"_id":"5fb1ba17e1af06001770b881","name":"Later Sinhalese","listId":294,"sublistId":"d","dateRange":{"_id":"5fb1b9f0e1af06001770a0d1","startDate":301,"endDate":1515},"troopOptions":[{"_id":"5fb1ba17e1af06001770b883","min":0,"max":1,"dateRange":null,"troopEntries":[{"_id":"5fb1ba17e1af06001770b884","troopTypeCode":"RDR","dismountTypeCode":null,"note":null}],"description":"Swordsmen","note":"","core":"all","battleCardEntries":[]},{"_id":"5fb1ba17e1af06001770b885","min":3,"max":6,"dateRange":null,"troopEntries":[{"_id":"5fb1ba17e1af06001770b886","troopTypeCode":"BLV","dismountTypeCode":null,"note":null}],"description":"Militia bowmen","note":"","core":"","battleCardEntries":[]}],"internalContingent":false,"armyListId":"5fb1b9f0e1af06001770a0cd","__v":0}}]},{"_id":"5fb1ba3de1af06001770f456","dateRange":{"_id":"5fb1ba3de1af06001770f457","startDate":1409,"endDate":1435},"note":null,"allyEntries":[{"_id":"5fb1ba3de1af06001770f458","name":"(Malacca Malays) Ming Chinese allies","allyArmyList":{"_id":"5fb1ba17e1af06001770b8e7","name":"Ming Expeditionary Force","listId":299,"sublistId":"z","dateRange":null,"troopOptions":[{"_id":"5fb1ba17e1af06001770b8e8","min":0,"max":1,"dateRange":{"_id":"5fb1ba17e1af06001770b8e9","startDate":1409,"endDate":1419},"troopEntries":[{"_id":"5fb1ba17e1af06001770b8ea","troopTypeCode":"HBW","dismountTypeCode":null,"note":null}],"description":"Chinese horse archers","note":"","core":"all","battleCardEntries":[]},{"_id":"5fb1ba17e1af06001770b8eb","min":0,"max":1,"dateRange":null,"troopEntries":[{"_id":"5fb1ba17e1af06001770b8ec","troopTypeCode":"HFT","dismountTypeCode":null,"note":null}],"description":"Chinese close-fighting infantry armed with mixed halberd-type weapons","note":"","core":"all","battleCardEntries":[]},{"_id":"5fb1ba17e1af06001770b8ed","min":0,"max":1,"dateRange":null,"troopEntries":[{"_id":"5fb1ba17e1af06001770b8ee","troopTypeCode":"ARC","dismountTypeCode":null,"note":null},{"_id":"5fb1ba17e1af06001770b8ef","troopTypeCode":"PAV","dismountTypeCode":null,"note":null}],"description":"Chinese bowmen or crossbowmen, separate or protected behind spearmen with shield","note":"","core":"all","battleCardEntries":[]}],"internalContingent":false,"__v":0}}]},{"_id":"5fb1ba3de1af06001770f459","dateRange":{"_id":"5fb1ba3de1af06001770f45a","startDate":1436,"endDate":1511},"note":null,"allyEntries":[{"_id":"5fb1ba3de1af06001770f45b","name":"(Malacca Malays) Javanese allies","allyArmyList":{"_id":"5fb1ba17e1af06001770b8db","name":"Javanese","listId":299,"sublistId":"c","dateRange":{"_id":"5fb1b9f0e1af06001770a10b","startDate":1222,"endDate":1511},"troopOptions":[{"_id":"5fb1ba17e1af06001770b8dd","min":2,"max":4,"dateRange":null,"troopEntries":[{"_id":"5fb1ba17e1af06001770b8de","troopTypeCode":"WRR","dismountTypeCode":null,"note":null}],"description":"Fierce fighters","note":"","core":"","battleCardEntries":[]},{"_id":"5fb1ba17e1af06001770b8df","min":1,"max":2,"dateRange":null,"troopEntries":[{"_id":"5fb1ba17e1af06001770b8e0","troopTypeCode":"BLV","dismountTypeCode":null,"note":null}],"description":"Bowmen","note":"","core":"","battleCardEntries":[]}],"internalContingent":false,"armyListId":"5fb1b9f0e1af06001770a107","__v":0}}]}]