[{"_id":"615351b403385c0016b88a70","dateRange":{"_id":"615351b403385c0016b88a71","startDate":951,"endDate":979},"note":null,"allyEntries":[{"_id":"615351b403385c0016b88a72","name":"Northern Han allies","allyArmyList":{"_id":"6153519b03385c0016b84a73","name":"Late Tang and Ten Kingdoms Chinese","listId":319,"sublistId":"a","dateRange":{"_id":"6153508c03385c0016b824f6","startDate":755,"endDate":979},"troopOptions":[{"_id":"6153519b03385c0016b84a75","min":0,"max":1,"dateRanges":[],"troopEntries":[{"_id":"6153519b03385c0016b84a76","troopTypeCode":"ARC","dismountTypeCode":null,"note":null}],"description":"Crossbowmen","note":"","core":"all","battleCardEntries":[]},{"_id":"6153519b03385c0016b84a77","min":0,"max":1,"dateRanges":[],"troopEntries":[{"_id":"6153519b03385c0016b84a78","troopTypeCode":"BLV","dismountTypeCode":null,"note":null}],"description":"Bowmen","note":"","core":"all","battleCardEntries":[]},{"_id":"6153519b03385c0016b84a79","min":1,"max":1,"dateRanges":[],"troopEntries":[{"_id":"6153519b03385c0016b84a7a","troopTypeCode":"LSP","dismountTypeCode":null,"note":null},{"_id":"6153519b03385c0016b84a7b","troopTypeCode":"HFT","dismountTypeCode":null,"note":null}],"description":"Spearmen, with or without shields","note":"","core":"all","battleCardEntries":[]},{"_id":"6153519b03385c0016b84a7c","min":1,"max":1,"dateRanges":[],"troopEntries":[{"_id":"6153519b03385c0016b84a7d","troopTypeCode":"RDR","dismountTypeCode":null,"note":null}],"description":"Vanguard swordsmen","note":"","core":"","battleCardEntries":[]},{"_id":"6153519b03385c0016b84a7e","min":0,"max":1,"dateRanges":[],"troopEntries":[{"_id":"6153519b03385c0016b84a7f","troopTypeCode":"WBD","dismountTypeCode":null,"note":"all"},{"_id":"6153519b03385c0016b84a80","troopTypeCode":"LFT","dismountTypeCode":null,"note":"all"}],"description":"Southern tribal auxiliaries","note":"","core":"","battleCardEntries":[]}],"internalContingent":false,"armyListId":"5fb1b9f2e1af06001770a26d","__v":0}}]},{"_id":"615351b403385c0016b88a73","dateRange":{"_id":"615351b403385c0016b88a74","startDate":1121,"endDate":1125},"note":null,"allyEntries":[{"_id":"615351b403385c0016b88a75","name":"Xi Xia allies","allyArmyList":{"_id":"6153519b03385c0016b84aea","name":"Western Xia","listId":324,"sublistId":"a","dateRange":{"_id":"6153508c03385c0016b8252b","startDate":982,"endDate":1227},"troopOptions":[{"_id":"6153519b03385c0016b84aec","min":1,"max":2,"dateRanges":[],"troopEntries":[{"_id":"6153519b03385c0016b84aed","troopTypeCode":"ECV","dismountTypeCode":null,"note":null}],"description":"Tangut nomad horsemen","note":"","core":"","battleCardEntries":[]},{"_id":"6153519b03385c0016b84aee","min":1,"max":1,"dateRanges":[],"troopEntries":[{"_id":"6153519b03385c0016b84aef","troopTypeCode":"HBW","dismountTypeCode":null,"note":null}],"description":"Tangut settled horse archers and nomad scouts","note":"","core":"","battleCardEntries":[]},{"_id":"6153519b03385c0016b84af0","min":0,"max":1,"dateRanges":[],"troopEntries":[{"_id":"6153519b03385c0016b84af1","troopTypeCode":"LFT","dismountTypeCode":null,"note":null}],"description":"Tangut foot treaders","note":"","core":"","battleCardEntries":[]},{"_id":"6153519b03385c0016b84af2","min":0,"max":1,"dateRanges":[],"troopEntries":[{"_id":"6153519b03385c0016b84af3","troopTypeCode":"HFT","dismountTypeCode":null,"note":null}],"description":"Chinese swordsmen or polearms","note":"","core":"all","battleCardEntries":[]},{"_id":"6153519b03385c0016b84af4","min":0,"max":1,"dateRanges":[],"troopEntries":[{"_id":"6153519b03385c0016b84af5","troopTypeCode":"BLV","dismountTypeCode":null,"note":null}],"description":"Chinese bowmen and crossbowmen","note":"","core":"all","battleCardEntries":[]}],"internalContingent":false,"armyListId":"5fb1b9f3e1af06001770a2a2","__v":0}}]},{"_id":"615351b403385c0016b88a76","dateRange":{"_id":"615351b403385c0016b88a77","startDate":1121,"endDate":1125},"note":null,"allyEntries":[{"_id":"615351b403385c0016b88a78","name":"Xi Xia allies -- all mounted","allyArmyList":{"_id":"6153519b03385c0016b84af6","name":"Western Xia (all mounted)","listId":324,"sublistId":"b","dateRange":{"_id":"6153508c03385c0016b82532","startDate":982,"endDate":1227},"troopOptions":[{"_id":"6153519b03385c0016b84af8","min":1,"max":3,"dateRanges":[],"troopEntries":[{"_id":"6153519b03385c0016b84af9","troopTypeCode":"ECV","dismountTypeCode":null,"note":null}],"description":"Tangut nomad horsemen","note":"","core":"","battleCardEntries":[]},{"_id":"6153519b03385c0016b84afa","min":1,"max":2,"dateRanges":[],"troopEntries":[{"_id":"6153519b03385c0016b84afb","troopTypeCode":"HBW","dismountTypeCode":null,"note":null}],"description":"Tangut settled horse archers and nomad scouts","note":"","core":"","battleCardEntries":[]}],"internalContingent":false,"armyListId":"5fb1b9f3e1af06001770a2a9","__v":0}}]}]