[{"_id":"6153519f03385c0016b8519d","dateRange":null,"note":null,"allyEntries":[{"_id":"6153519f03385c0016b8519e","name":"Phoenician allies","allyArmyList":{"_id":"6153518e03385c0016b83645","name":"Early Cypriot and Phoenician","listId":32,"sublistId":"a","dateRange":{"_id":"6153507303385c0016b81698","startDate":-1000,"endDate":-665},"troopOptions":[],"internalContingent":false,"armyListId":"5fb1b9dae1af0600177093f2","__v":0}}]},{"_id":"6153519f03385c0016b8519f","dateRange":null,"note":null,"allyEntries":[{"_id":"6153519f03385c0016b851a0","name":"Phoenician allies","allyArmyList":{"_id":"6153518e03385c0016b83647","name":"Middle Cypriot and Phoenician","listId":32,"sublistId":"b","dateRange":{"_id":"6153507303385c0016b8169f","startDate":-664,"endDate":-351},"troopOptions":[{"_id":"6153518e03385c0016b83649","min":0,"max":1,"dateRanges":[{"_id":"6153518e03385c0016b8364a","startDate":-664,"endDate":-490}],"troopEntries":[{"_id":"6153518e03385c0016b8364b","troopTypeCode":"CHT","dismountTypeCode":null,"note":null}],"description":"4-horse chariots with three crewmen","note":"","core":"","battleCardEntries":[]},{"_id":"6153518e03385c0016b8364c","min":2,"max":5,"dateRanges":[],"troopEntries":[{"_id":"6153518e03385c0016b8364d","troopTypeCode":"LFT","dismountTypeCode":null,"note":null},{"_id":"6153518e03385c0016b8364e","troopTypeCode":"HFT","dismountTypeCode":null,"note":null}],"description":"Spearmen or hoplites","note":"","core":"all","battleCardEntries":[]},{"_id":"6153518e03385c0016b8364f","min":0,"max":1,"dateRanges":[],"troopEntries":[{"_id":"6153518e03385c0016b83650","troopTypeCode":"BLV","dismountTypeCode":null,"note":null}],"description":"Bowmen","note":"","core":"all","battleCardEntries":[]}],"internalContingent":false,"armyListId":"5fb1b9dae1af0600177093f9","__v":0}}]},{"_id":"6153519f03385c0016b851a1","dateRange":null,"note":null,"allyEntries":[{"_id":"6153519f03385c0016b851a2","name":"Aramaean allies","allyArmyList":{"_id":"6153518e03385c0016b83620","name":"Early Syro-Hittite","listId":30,"sublistId":"a","dateRange":{"_id":"6153507303385c0016b81683","startDate":-1100,"endDate":-901},"troopOptions":[{"_id":"6153518e03385c0016b83622","min":0,"max":1,"dateRanges":[],"troopEntries":[{"_id":"6153518e03385c0016b83623","troopTypeCode":"CHT","dismountTypeCode":null,"note":null}],"description":"2-horse chariots with two crewmen","note":"","core":"","battleCardEntries":[]},{"_id":"6153518e03385c0016b83624","min":2,"max":3,"dateRanges":[],"troopEntries":[{"_id":"6153518e03385c0016b83625","troopTypeCode":"LFT","dismountTypeCode":null,"note":null}],"description":"Militia spearmen","note":"","core":"all","battleCardEntries":[]},{"_id":"6153518e03385c0016b83626","min":0,"max":2,"dateRanges":[],"troopEntries":[{"_id":"6153518e03385c0016b83627","troopTypeCode":"BLV","dismountTypeCode":null,"note":null}],"description":"Militia bowmen","note":"","core":"all","battleCardEntries":[]},{"_id":"6153518e03385c0016b83628","min":0,"max":2,"dateRanges":[],"troopEntries":[{"_id":"6153518e03385c0016b83629","troopTypeCode":"SKM","dismountTypeCode":null,"note":null}],"description":"Militia slingers","note":"","core":"","battleCardEntries":[]}],"internalContingent":false,"armyListId":"5fb1b9dae1af0600177093dd","__v":0}}]},{"_id":"6153519f03385c0016b851a3","dateRange":null,"note":null,"allyEntries":[{"_id":"6153519f03385c0016b851a4","name":"Aramaean allies","allyArmyList":{"_id":"6153518e03385c0016b8362a","name":"Later Syro-Hittite","listId":30,"sublistId":"b","dateRange":{"_id":"6153507303385c0016b8168a","startDate":-900,"endDate":-710},"troopOptions":[{"_id":"6153518e03385c0016b8362c","min":1,"max":2,"dateRanges":[],"troopEntries":[{"_id":"6153518e03385c0016b8362d","troopTypeCode":"CHT","dismountTypeCode":null,"note":null}],"description":"2-horse chariots with two crewmen, or 3- or 4-horse chariots with three crewmen","note":"","core":"","battleCardEntries":[]},{"_id":"6153518e03385c0016b8362e","min":1,"max":2,"dateRanges":[],"troopEntries":[{"_id":"6153518e03385c0016b8362f","troopTypeCode":"LFT","dismountTypeCode":null,"note":null}],"description":"Militia spearmen","note":"","core":"all","battleCardEntries":[]},{"_id":"6153518e03385c0016b83630","min":0,"max":1,"dateRanges":[],"troopEntries":[{"_id":"6153518e03385c0016b83631","troopTypeCode":"BLV","dismountTypeCode":null,"note":null}],"description":"Militia bowmen","note":"","core":"all","battleCardEntries":[]},{"_id":"6153518e03385c0016b83632","min":0,"max":1,"dateRanges":[],"troopEntries":[{"_id":"6153518e03385c0016b83633","troopTypeCode":"SKM","dismountTypeCode":null,"note":null}],"description":"Militia slingers","note":"","core":"","battleCardEntries":[]}],"internalContingent":false,"armyListId":"5fb1b9dae1af0600177093e4","__v":0}}]},{"_id":"6153519f03385c0016b851a5","dateRange":{"_id":"6153519f03385c0016b851a6","startDate":-743,"endDate":-720},"note":null,"allyEntries":[{"_id":"6153519f03385c0016b851a7","name":"Egyptian allies","allyArmyList":{"_id":"6153518f03385c0016b83708","name":"Libyan Egyptian","listId":43,"sublistId":"a","dateRange":{"_id":"6153507403385c0016b81710","startDate":-946,"endDate":-712},"troopOptions":[{"_id":"6153518f03385c0016b8370a","min":0,"max":1,"dateRanges":[],"troopEntries":[{"_id":"6153518f03385c0016b8370b","troopTypeCode":"CHT","dismountTypeCode":null,"note":null}],"description":"2-horse chariots","note":"","core":"","battleCardEntries":[]},{"_id":"6153518f03385c0016b8370c","min":1,"max":3,"dateRanges":[],"troopEntries":[{"_id":"6153518f03385c0016b8370d","troopTypeCode":"WRR","dismountTypeCode":null,"note":null}],"description":"Meshwesh","note":"","core":"all","battleCardEntries":[]},{"_id":"6153518f03385c0016b8370e","min":1,"max":2,"dateRanges":[],"troopEntries":[{"_id":"6153518f03385c0016b8370f","troopTypeCode":"RBL","dismountTypeCode":null,"note":null}],"description":"Libu, Palestinian, or Arab javelinmen","note":"","core":"","battleCardEntries":[]},{"_id":"6153518f03385c0016b83710","min":0,"max":1,"dateRanges":[],"troopEntries":[{"_id":"6153518f03385c0016b83711","troopTypeCode":"SKM","dismountTypeCode":null,"note":null}],"description":"Nubian or Libu skirmishing bowmen","note":"","core":"","battleCardEntries":[]},{"_id":"6153518f03385c0016b83712","min":0,"max":1,"dateRanges":[],"troopEntries":[{"_id":"6153518f03385c0016b83713","troopTypeCode":"LFT","dismountTypeCode":null,"note":null}],"description":"Egyptian infantry","note":"","core":"all","battleCardEntries":[]},{"_id":"6153518f03385c0016b83714","min":0,"max":1,"dateRanges":[],"troopEntries":[{"_id":"6153518f03385c0016b83715","troopTypeCode":"BLV","dismountTypeCode":null,"note":null}],"description":"Egyptian bowmen","note":"","core":"all","battleCardEntries":[]}],"internalContingent":false,"armyListId":"5fb1b9dbe1af06001770946a","__v":0}}]},{"_id":"6153519f03385c0016b851a8","dateRange":{"_id":"6153519f03385c0016b851a9","startDate":-701,"endDate":-701},"note":null,"allyEntries":[{"_id":"6153519f03385c0016b851aa","name":"Egyptian allies","allyArmyList":{"_id":"6153518f03385c0016b83724","name":"Kushite Egyptian","listId":44,"sublistId":"b","dateRange":{"_id":"6153507403385c0016b8171f","startDate":-745,"endDate":-593},"troopOptions":[{"_id":"6153518f03385c0016b83726","min":0,"max":1,"dateRanges":[],"troopEntries":[{"_id":"6153518f03385c0016b83727","troopTypeCode":"CHT","dismountTypeCode":null,"note":null}],"description":"2-horse chariots (also possibly 4-horse chariots with three crewmen after 727 BC)","note":"","core":"","battleCardEntries":[]},{"_id":"6153518f03385c0016b83728","min":0,"max":1,"dateRanges":[],"troopEntries":[{"_id":"6153518f03385c0016b83729","troopTypeCode":"JCV","dismountTypeCode":null,"note":null}],"description":"Kushite horsemen","note":"","core":"","battleCardEntries":[]},{"_id":"6153518f03385c0016b8372a","min":1,"max":3,"dateRanges":[],"troopEntries":[{"_id":"6153518f03385c0016b8372b","troopTypeCode":"ARC","dismountTypeCode":null,"note":null},{"_id":"6153518f03385c0016b8372c","troopTypeCode":"SKM","dismountTypeCode":null,"note":null}],"description":"Kushite bowmen","note":"","core":"all","battleCardEntries":[]},{"_id":"6153518f03385c0016b8372d","min":0,"max":1,"dateRanges":[],"troopEntries":[{"_id":"6153518f03385c0016b8372e","troopTypeCode":"LFT","dismountTypeCode":null,"note":null}],"description":"Kushite javelinmen","note":"","core":"","battleCardEntries":[]},{"_id":"6153518f03385c0016b8372f","min":0,"max":1,"dateRanges":[],"troopEntries":[{"_id":"6153518f03385c0016b83730","troopTypeCode":"SKM","dismountTypeCode":null,"note":null}],"description":"Kushite skirmishing slingers","note":"","core":"","battleCardEntries":[]}],"internalContingent":false,"armyListId":"5fb1b9dbe1af060017709478","__v":0}}]}]